Workbook

Sheet Extracting Company Contact Info
B1: Company Name | C1: Contact Name | D1: Address | E1: Phone | F1: Email | G1: Category
A2: {=XLOOKUP(B2&E2, Sheet1!B2:B397&Sheet1!C2:C397, Sheet1!A2:C397, "Category Not Found", 0)} -> #N/A | B2: 10X Builders Inc. | C2: Alani Fua | D2: 105 E 580 N, Vineyard, UT 84059 | E2: (801) 803-8931 | F2: alani@10XBuilders.com | G2: {=IF(ISBLANK(B2:B795), "", XLOOKUP(B2:B795, Sheet1!D2:D397, Sheet1!B2:B161, "Category Not Found", 0))} -> #REF!
B3: 2-10 Home Buyers Warranty | C3: Jake Echevarria | D3: 10375 E Harvard Ave, #100, Denver, CO 80231 | E3: (800) 488-8844 | F3: jechevarria@2-10.com | G3: {=IF(ISBLANK(B3:B796), "", XLOOKUP(B3:B796, Sheet1!A3:A162, Sheet1!C3:C162, "Category Not Found", 0))} -> #REF!
B4: 7D Construction | C4: Mike Balls | D4: 13133s Running Bear Ln, Draper, UT 84020 | E4: (801) 514-8051 | F4: Mike@7dutah.com | G4: {=IF(ISBLANK(B4:B797), "", XLOOKUP(B4:B797, Sheet1!A4:A163, Sheet1!C4:C163, "Category Not Found", 0))} -> #REF!
B5: A Plus Garage Doors | C5: Job Booker | D5: 974 W 14420 S, Bluffdale, UT 84065 | E5: (801) 590-3106 | F5: support@aplusdoor.com | G5: {=IF(ISBLANK(B5:B798), "", XLOOKUP(B5:B798, Sheet1!A5:A164, Sheet1!C5:C164, "Category Not Found", 0))} -> #REF!
B6: A&A Staffing Solutions Inc. | C6: Alex Morales | D6: 709 N 1200 W, Orem, UT 84057 | E6: (801) 814-4949 | F6: alexmcorporation@gmail.com | G6: {=IF(ISBLANK(B6:B799), "", XLOOKUP(B6:B799, Sheet1!A6:A165, Sheet1!C6:C165, "Category Not Found", 0))} -> #REF!
B7: Above and Beyond Cleaning | C7: Lindsay Islas | D7: 3768 N University Ave, #202, Provo, UT 84604 | E7: (801) 400-1819 | F7: blindsay101@gmail.com | G7: {=IF(ISBLANK(B7:B800), "", XLOOKUP(B7:B800, Sheet1!A7:A166, Sheet1!C7:C166, "Category Not Found", 0))} -> #REF!
B8: Acapulco Marble and Granite Inc | C8: Brenda Benitez | D8: 891 S 490 W, #G, Pleasant Grove, UT 84062 | E8: (385) 216-8993 | F8: brenda@acapulcomarble.com | G8: {=IF(ISBLANK(B8:B801), "", XLOOKUP(B8:B801, Sheet1!A8:A167, Sheet1!C8:C167, "Category Not Found", 0))} -> #REF!
B9: Accena Group | C9: Ken Adams | D9: 361 W 1200 N, American Fork, UT 84003 | E9: (801) 615-2930 | F9: support@StormwaterPlan.com | G9: {=IF(ISBLANK(B9:B802), "", XLOOKUP(B9:B802, Sheet1!A9:A168, Sheet1!C9:C168, "Category Not Found", 0))} -> #REF!
B10: Ace Coatings | C10: Jace Kelly | D10: 1583 S 2520 E, Spanish Fork, UT 84660 | E10: (385) 269-0060 | F10: info@acecoatingsutah.com | G10: {=IF(ISBLANK(B10:B803), "", XLOOKUP(B10:B803, Sheet1!A10:A169, Sheet1!C10:C169, "Category Not Found", 0))} -> #REF!
B11: Acute Engineering | C11: Alison Simpson | D11: 744 S 400 E, Orem, UT 84097 | E11: (801) 229-9020 | F11: brandon@acuteengineering.com | G11: {=IF(ISBLANK(B11:B804), "", XLOOKUP(B11:B804, Sheet1!A11:A170, Sheet1!C11:C170, "Category Not Found", 0))} -> #REF!
B12: Adams Construction Forensics | C12: Ken Adams | D12: 361 W 1200 N, American Fork, UT 84003 | E12: (801) 367-2746 | F12: ken.adams.cm@gmail.com | G12: {=IF(ISBLANK(B12:B805), "", XLOOKUP(B12:B805, Sheet1!A12:A171, Sheet1!C12:C171, "Category Not Found", 0))} -> #REF!
B13: Adamson Construction Company, LC | C13: Kay B. Adamson | D13: 820 N 1200 E, Lehi, UT 84043 | E13: (801) 360-0136 | F13: kay_b_adamson@yahoo.com | G13: {=IF(ISBLANK(B13:B806), "", XLOOKUP(B13:B806, Sheet1!A13:A172, Sheet1!C13:C172, "Category Not Found", 0))} -> #REF!
B14: Advanced Aqua Systems | C14: Chris Phillips | D14: 250 Red Cliff Dr, #4B-224, St George, UT 84790 | E14: (435) 817-2600 | F14: service@advancedaquasystems.com | G14: {=IF(ISBLANK(B14:B807), "", XLOOKUP(B14:B807, Sheet1!A14:A173, Sheet1!C14:C173, "Category Not Found", 0))} -> #REF!
... B107: Blue Water Excavation | C107: Mike Trotter | D107: 588 N 2670 W, Provo, UT 84601 | E107: (801) 687-1697 | F107: trotterlandscape@gmail.com | G107: {=IF(ISBLANK(B107:B900), "", XLOOKUP(B107:B900, Sheet1!A107:A266, Sheet1!C107:C266, "Category Not Found", 0))} -> #REF!
B108: Blueprinted Homes | C108: 825 N 730 E, American Fork, UT 84003 | D108: (801) 830-9086 | E108: blueprintedhomes@gmail.com | G108: {=IF(ISBLANK(B108:B901), "", XLOOKUP(B108:B901, Sheet1!A108:A267, Sheet1!C108:C267, "Category Not Found", 0))} -> #REF!
B109: Bluroc Development | C109: Jason Valgardson | D109: 1512 W 2100 N, Pleasant Grove, UT 84062 | E109: (801) 420-4739 | F109: blurocdevelopment@gmail.com | G109: {=IF(ISBLANK(B109:B902), "", XLOOKUP(B109:B902, Sheet1!A109:A268, Sheet1!C109:C268, "Category Not Found", 0))} -> #REF!
B110: Blvd Home | C110: Cam Hatanaka | D110: 390 N Mall Dr, St George, UT 84790 | E110: (435) 986-3100 | F110: cam.hatanaka@blvdhome.com | G110: {=IF(ISBLANK(B110:B903), "", XLOOKUP(B110:B903, Sheet1!A110:A269, Sheet1!C110:C269, "Category Not Found", 0))} -> #REF!
B111: Bone Bucket | C111: Charles Bones Leavitt | D111: 653 N 500 E, Pleasant Grove, UT 84062 | E111: (385) 221-9106 | F111: bonebucketwashout@gmail.com | G111: {=IF(ISBLANK(B111:B904), "", XLOOKUP(B111:B904, Sheet1!A111:A270, Sheet1!C111:C270, "Category Not Found", 0))} -> #REF!
B112: Bonsai Flooring | C112: Brook Smith | D112: 1501 S Mill Rd, Spanish Fork, UT 84660 | E112: (801) 400-6837 | F112: brook@bonsaiflooring.com | G112: {=IF(ISBLANK(B112:B905), "", XLOOKUP(B112:B905, Sheet1!A112:A271, Sheet1!C112:C271, "Category Not Found", 0))} -> #REF!
B113: Bookkeeping for Contractors | C113: Kierston Ward | D113: 2140 W 700 S, #2, Springville, UT 84663 | E113: (801) 927-0299 | F113: admin@bookkeepingforcontractors.com | G113: {=IF(ISBLANK(B113:B906), "", XLOOKUP(B113:B906, Sheet1!A113:A272, Sheet1!C113:C272, "Category Not Found", 0))} -> #REF!
B114: Boss Drywall inc. | C114: Edward Bustillos | D114: 7056 W Hightower Rd, West Valley City, UT 84081 | E114: (801) 824-7667 | F114: bossdrywallinc@gmail.com | G114: {=IF(ISBLANK(B114:B907), "", XLOOKUP(B114:B907, Sheet1!A114:A273, Sheet1!C114:C273, "Category Not Found", 0))} -> #REF!
B115: Boulder Beach | C115: Jessica Krantz | D115: 452 W Center St, #107, Pleasant Grove, UT 84062 | E115: (808) 772-0367 | F115: shopboulderbeach@gmail.com | G115: {=IF(ISBLANK(B115:B908), "", XLOOKUP(B115:B908, Sheet1!A115:A274, Sheet1!C115:C274, "Category Not Found", 0))} -> #REF!
B116: Boxwood Interiors | C116: Jeremy Palmer | D116: 72 N Main St, Spanish Fork, UT 84660 | E116: (801) 785-6858 | F116: jeremy@boxwood-home.com | G116: {=IF(ISBLANK(B116:B909), "", XLOOKUP(B116:B909, Sheet1!A116:A275, Sheet1!C116:C275, "Category Not Found", 0))} -> #REF!
B117: Brick Design Co | C117: Robert Backmore | D117: 428 UT-198, #B, Salem, UT 84653 | E117: (801) 850-8880 | F117: robert@brickdesign.co | G117: {=IF(ISBLANK(B117:B910), "", XLOOKUP(B117:B910, Sheet1!A117:A276, Sheet1!C117:C276, "Category Not Found", 0))} -> #REF!
B118: Bright Homes | C118: Jon Traveller | D118: 3000 N Triumph Blvd, #100, Lehi, UT 84043 | E118: (801) 420-5028 | F118: jon@brighthomesutah.com | G118: {=IF(ISBLANK(B118:B911), "", XLOOKUP(B118:B911, Sheet1!A118:A277, Sheet1!C118:C277, "Category Not Found", 0))} -> #REF!
B119: Brinkerhoff Custom Construction | C119: Dustin Brinkerhoff | D119: 1911 W Yarrow Dr, Mapleton, UT 84663 | E119: (801) 404-1960 | F119: dustin@brinkerhoffcc.com | G119: {=IF(ISBLANK(B119:B912), "", XLOOKUP(B119:B912, Sheet1!A119:A278, Sheet1!C119:C278, "Category Not Found", 0))} -> #REF!
B120: Brinkerhoff Drywall | C120: Ron Brinkerhoff | D120: 4068 W 7300 S, Benjamin, UT 84660 | E120: (801) 404-0231 | F120: brinkerhoffdrywallllc@gmail.com | G120: {=IF(ISBLANK(B120:B913), "", XLOOKUP(B120:B913, Sheet1!A120:A279, Sheet1!C120:C279, "Category Not Found", 0))} -> #REF!
... B652: Stage 7 Design | C652: Samantha Carson | D652: 6575 W 7300 N, American Fork, UT 84003 | E652: (801) 763-7370 | F652: stage7design@gmail.com | G652: {=IF(ISBLANK(B652:B1445), "", XLOOKUP(B652:B1445, Sheet1!A652:A811, Sheet1!C652:C811, "Category Not Found", 0))} -> #REF!
A653: Category | B653: Stan Barlow Construction LLC | C653: Trevor Barlow | D653: 876 N 700 E, Mapleton, UT 84664 | E653: (801) 628-1790 | F653: trevor@stanbarlowconstruction.com | G653: {=IF(ISBLANK(B653:B1446), "", XLOOKUP(B653:B1446, Sheet1!A653:A812, Sheet1!C653:C812, "Category Not Found", 0))} -> #REF!
A654: ==XLOOKUP(B2&E2, Sheet1!A2:A161&Sheet1!B2:B161, Sheet1!C2:C161, "Category Not Found", 0) -> #ERROR! | B654: Stanley Contracting | C654: Nate Stanley | D654: 815 N Spring Ln, Spanish Fork, UT 84660 | E654: (801) 717-6976 | F654: nate@stanleycontracting.net | G654: {=IF(ISBLANK(B654:B1447), "", XLOOKUP(B654:B1447, Sheet1!A654:A813, Sheet1!C654:C813, "Category Not Found", 0))} -> #REF!
B655: Static Marketing | C655: Brayden Tomicic | D655: 24 W Main St, #113, Lehi, UT 84043 | E655: (801) 472-3278 | F655: brayden@workwithstatic.com | G655: {=IF(ISBLANK(B655:B1448), "", XLOOKUP(B655:B1448, Sheet1!A655:A814, Sheet1!C655:C814, "Category Not Found", 0))} -> #REF!
B656: Steiner Painting Inc. | C656: Jesse Lee Steiner | D656: 1748 Anderson Ave, Springville, UT 84663 | E656: (801) 368-1312 | F656: jesse.steiner@gmail.com | G656: {=IF(ISBLANK(B656:B1449), "", XLOOKUP(B656:B1449, Sheet1!A656:A815, Sheet1!C656:C815, "Category Not Found", 0))} -> #REF!
B657: Sterling Structures Inc. | C657: Rick Radley | D657: 1458 E 300 S, Pleasant Grove, UT 84062 | E657: (801) 787-7983 | F657: sterlingframes4u@gmail.com | G657: {=IF(ISBLANK(B657:B1450), "", XLOOKUP(B657:B1450, Sheet1!A657:A816, Sheet1!C657:C816, "Category Not Found", 0))} -> #REF!
B658: Steven Dailey Construction, Inc. | C658: Stephanie Dailey | D658: 12441 S 900 E, #185, Draper, UT 84020 | E658: (801) 673-1614 | F658: stephanie@stevendailey.com | G658: {=IF(ISBLANK(B658:B1451), "", XLOOKUP(B658:B1451, Sheet1!A658:A817, Sheet1!C658:C817, "Category Not Found", 0))} -> #REF!
B659: Stone Mountain Castings & Design | C659: Mandii Olsen | D659: 140 N 1200 W, Orem, UT 84057 | E659: (801) 495-9797 | F659: molsen@stonemt.net | G659: {=IF(ISBLANK(B659:B1452), "", XLOOKUP(B659:B1452, Sheet1!A659:A818, Sheet1!C659:C818, "Category Not Found", 0))} -> #REF!
B660: Stonehenge Fence & Deck | C660: Vicki Jacobson | D660: 4084 S 300 W, Murray, UT 84107 | E660: (801) 607-5733 | F660: vicki@stonehengefence.com | G660: {=IF(ISBLANK(B660:B1453), "", XLOOKUP(B660:B1453, Sheet1!A660:A819, Sheet1!C660:C819, "Category Not Found", 0))} -> #REF!
B661: Stoneworld Properties | C661: Rhett Robison | D661: 1524 E 715 S, Mapleton, UT 84664 | E661: (801) 860-7625 | F661: crstoneinc@gmail.com | G661: {=IF(ISBLANK(B661:B1454), "", XLOOKUP(B661:B1454, Sheet1!A661:A820, Sheet1!C661:C820, "Category Not Found", 0))} -> #REF!
B662: Stormwater Utah | C662: David Duvall | D662: PO Box 554, Spanish Fork, UT 84660 | E662: (385) 448-7724 | F662: david@stormwaterUtah.com | G662: {=IF(ISBLANK(B662:B1455), "", XLOOKUP(B662:B1455, Sheet1!A662:A821, Sheet1!C662:C821, "Category Not Found", 0))} -> #REF!
B663: Strong and Hanni PC | C663: Matthew Jones | D663: 9350 S 150 E, #820, Sandy, UT 84070 | E663: (801) 532-7080 | F663: pbarlow@strongandhanni.com | G663: {=IF(ISBLANK(B663:B1456), "", XLOOKUP(B663:B1456, Sheet1!A663:A822, Sheet1!C663:C822, "Category Not Found", 0))} -> #REF!
B664: Studz Construction | C664: Rob Snyder | D664: 706 E 600 S, Salem, UT 84653 | E664: (801) 735-9771 | F664: rob@studzutah.com | G664: {=IF(ISBLANK(B664:B1457), "", XLOOKUP(B664:B1457, Sheet1!A664:A823, Sheet1!C664:C823, "Category Not Found", 0))} -> #REF!
B665: Summit Construction Services LLC | C665: Brady Jensen | D665: 448 N 1750 W, #B, Springville, UT 84663 | E665: (801) 762-7500 | F665: bradyj.jensen@gmail.com | G665: {=IF(ISBLANK(B665:B1458), "", XLOOKUP(B665:B1458, Sheet1!A665:A824, Sheet1!C665:C824, "Category Not Found", 0))} -> #REF!
B666: Summit Fasteners | C666: Ted Pennington | D666: 42 N Geneva Rd, Orem, UT 84057 | E666: (801) 224-3881 | F666: mistypennington74@gmail.com | G666: {=IF(ISBLANK(B666:B1459), "", XLOOKUP(B666:B1459, Sheet1!A666:A825, Sheet1!C666:C825, "Category Not Found", 0))} -> #REF!
... B795: Zamp HR | C795: Isaac Allred | D795: 384 S 400 W, #120, Lindon, UT 84042 | E795: (801) 377-1190 | F795: isaac@zamphr.com | G795: {=IF(ISBLANK(B795:B1588), "", XLOOKUP(B795:B1588, Sheet1!A795:A954, Sheet1!C795:C954, "Category Not Found", 0))} -> Category Not Found

Sheet Sheet1
A1: Category | B1: Company Name | C1: Phone Number | D1: Category Filled
A2: Acoustic Specialists | B2: NuAcoustics | C2: (801) 400-7255 | D2: =IF(ISBLANK(A2), D1, A2) -> Acoustic Specialists
A3: Additions | B3: Jerry Stubbs Construction | C3: (801) 822-1621 | D3: =IF(ISBLANK(A3), D2, A3) -> Additions
B4: The Workman Company Inc | C4: (801) 368-3433 | D4: =IF(ISBLANK(A4), D3, A4) -> Additions
A5: Advertising/Promotions | B5: Anderson Monograms | C5: (801) 224-9744 | D5: =IF(ISBLANK(A5), D4, A5) -> Advertising/Promotions
B6: Logo Promotions | C6: (801) 592-4900 | D6: =IF(ISBLANK(A6), D5, A6) -> Advertising/Promotions
B7: Relic Agency | C7: (801) 692-7345 | D7: =IF(ISBLANK(A7), D6, A7) -> Advertising/Promotions
B8: Safeguard Print Promote | C8: (801) 226-2730 | D8: =IF(ISBLANK(A8), D7, A8) -> Advertising/Promotions
B9: Utah Valley Magazine | C9: (801) 802-0200 | D9: =IF(ISBLANK(A9), D8, A9) -> Advertising/Promotions
A10: Air Barriers | B10: Elite Energy Solutions | C10: (801) 610-9779 | D10: =IF(ISBLANK(A10), D9, A10) -> Air Barriers
A11: Appliances | B11: Blvd Home | C11: (435) 986-3100 | D11: =IF(ISBLANK(A11), D10, A11) -> Appliances
B12: Contract Appliance Sales | C12: (801) 600-0800 | D12: =IF(ISBLANK(A12), D11, A12) -> Appliances
B13: Ferguson Bath, Kitchen & Lighting Gallery | C13: (801) 463-8340 | D13: =IF(ISBLANK(A13), D12, A13) -> Appliances
B14: Mountain Land Design | C14: (801) 466-0990 | D14: =IF(ISBLANK(A14), D13, A14) -> Appliances
B15: RC Willey Home Furnishings | C15: (801) 461-3933 | D15: =IF(ISBLANK(A15), D14, A15) -> Appliances
B16: Roth Living | C16: (801) 582-5552 | D16: =IF(ISBLANK(A16), D15, A16) -> Appliances
A17: Accounting | B17: Bookkeeping for Contractors | C17: (801) 927-0299 | D17: =IF(ISBLANK(A17), D16, A17) -> Accounting
B18: Larson and Company | C18: (801) 798-3545 | D18: =IF(ISBLANK(A18), D17, A18) -> Accounting
B19: Premier Tech Partners | C19: (801) 205-4427 | D19: =IF(ISBLANK(A19), D18, A19) -> Accounting
B20: Squire & Company | C20: (801) 225-6900 | D20: =IF(ISBLANK(A20), D19, A20) -> Accounting
A21: Architectural Services | B21: Archer & Buchanan Architecture, Ltd. | C21: (610) 692-9112 | D21: =IF(ISBLANK(A21), D20, A21) -> Architectural Services
B22: Atrium Architecture Engineering & Design | C22: (801) 435-5565 | D22: =IF(ISBLANK(A22), D21, A22) -> Architectural Services
B23: BDC Home Design | C23: (801) 367-0801 | D23: =IF(ISBLANK(A23), D22, A23) -> Architectural Services
B24: BK Virtual Homes | C24: (385) 479-1005 | D24: =IF(ISBLANK(A24), D23, A24) -> Architectural Services
B25: Blueprinted Homes | C25: (801) 830-9086 | D25: =IF(ISBLANK(A25), D24, A25) -> Architectural Services
B26: Carrick Custom Home Design | C26: (801) 794-0220 | D26: =IF(ISBLANK(A26), D25, A26) -> Architectural Services
B27: CoFi | C27: (801) 471-1286 | D27: =IF(ISBLANK(A27), D26, A27) -> Architectural Services
B28: Curtis Design Group | C28: (385) 999-5655 | D28: =IF(ISBLANK(A28), D27, A28) -> Architectural Services
B29: Habitations Residential Design Group | C29: (801) 476-1860 | D29: =IF(ISBLANK(A29), D28, A29) -> Architectural Services
B30: Harris Architecture | C30: (801) 377-6303 | D30: =IF(ISBLANK(A30), D29, A30) -> Architectural Services
B31: Hebdon Studios | C31: (801) 618-6719 | D31: =IF(ISBLANK(A31), D30, A31) -> Architectural Services
B32: Home Base | C32: (719) 331-9296 | D32: =IF(ISBLANK(A32), D31, A32) -> Architectural Services
B33: Jeff Adams Design, LLC | C33: (801) 916-4925 | D33: =IF(ISBLANK(A33), D32, A33) -> Architectural Services
... B42: Upwall Design Architects | C42: (801) 485-0708 | D42: =IF(ISBLANK(A42), D41, A42) -> Architectural Services
A43: Banks | B43: AltaBank | C43: (801) 642-3416 | D43: =IF(ISBLANK(A43), D42, A43) -> Banks
B44: Altabank, Division of Glacier Bank | C44: (801) 316-4649 | D44: =IF(ISBLANK(A44), D43, A44) -> Banks
B45: Bank of Utah | C45: (801) 409-5122 | D45: =IF(ISBLANK(A45), D44, A45) -> Banks
B46: Capital Community Bank | C46: (801) 669-5722 | D46: =IF(ISBLANK(A46), D45, A46) -> Banks
B47: Capital One | C47: (801) 310-3142 | D47: =IF(ISBLANK(A47), D46, A47) -> Banks
B48: Central Bank | C48: (801) 655-2117 | D48: =IF(ISBLANK(A48), D47, A48) -> Banks
B49: Hillcrest Bank | C49: (801) 426-0165 | D49: =IF(ISBLANK(A49), D48, A49) -> Banks
B50: U.S. Bank | C50: (801) 787-5514 | D50: =IF(ISBLANK(A50), D49, A50) -> Banks
B51: Washington Federal | C51: (801) 571-4271 | D51: =IF(ISBLANK(A51), D50, A51) -> Banks
B52: Zions Bank | C52: (801) 370-4100 | D52: =IF(ISBLANK(A52), D51, A52) -> Banks
A53: Building Materials/Supplies | B53: Builders FirstSource | C53: (801) 504-9507 | D53: =IF(ISBLANK(A53), D52, A53) -> Building Materials/Supplies
B54: Cambria | C54: (801) 200-8911 | D54: =IF(ISBLANK(A54), D53, A54) -> Building Materials/Supplies
B55: Clydeco Building Supplies | C55: (801) 489-9481 | D55: =IF(ISBLANK(A55), D54, A55) -> Building Materials/Supplies
B56: FastenMaster | C56: (800) 518-3569 | D56: =IF(ISBLANK(A56), D55, A56) -> Building Materials/Supplies
B57: Interstate Brick Company | C57: (801) 280-5200 | D57: =IF(ISBLANK(A57), D56, A57) -> Building Materials/Supplies
B58: J.M. Thomas | C58: (801) 940-2316 | D58: =IF(ISBLANK(A58), D57, A58) -> Building Materials/Supplies
B59: Louisiana Pacific | C59: (385) 246-6338 | D59: =IF(ISBLANK(A59), D58, A59) -> Building Materials/Supplies
B60: Lowe's | C60: (801) 201-9597 | D60: =IF(ISBLANK(A60), D59, A60) -> Building Materials/Supplies
B61: Mountainview Builders Supply, Inc | C61: (801) 523-8382 | D61: =IF(ISBLANK(A61), D60, A61) -> Building Materials/Supplies
B62: Old Mill Building Products | C62: (385) 224-6521 | D62: =IF(ISBLANK(A62), D61, A62) -> Building Materials/Supplies
B63: Quality Powder Coating | C63: (801) 794-1816 | D63: =IF(ISBLANK(A63), D62, A63) -> Building Materials/Supplies
B64: Ready Made Trusses & Builders' Supply | C64: (801) 419-2677 | D64: =IF(ISBLANK(A64), D63, A64) -> Building Materials/Supplies
B65: Ruck | C65: (385) 332-8057 | D65: =IF(ISBLANK(A65), D64, A65) -> Building Materials/Supplies
... B69: Sunroc | C69: (801) 722-2135 | D69: =IF(ISBLANK(A69), D68, A69) -> Building Materials/Supplies
A70: Cabinets | B70: Built Cabinets | C70: (385) 384-0018 | D70: =IF(ISBLANK(A70), D69, A70) -> Cabinets
B71: Cabinetry by Karman | C71: (801) 268-3581 | D71: =IF(ISBLANK(A71), D70, A71) -> Cabinets
B72: Christopher Scott Cabinetry | C72: (801) 319-0213 | D72: =IF(ISBLANK(A72), D71, A72) -> Cabinets
B73: Closet Factory | C73: (801) 972-5757 | D73: =IF(ISBLANK(A73), D72, A73) -> Cabinets
B74: Excel Cabinets | C74: (801) 463-3600 | D74: =IF(ISBLANK(A74), D73, A74) -> Cabinets
B75: Houtz Woodworks | C75: (801) 420-3240 | D75: =IF(ISBLANK(A75), D74, A75) -> Cabinets
B76: K4 Cabinetry | C76: (385) 244-8647 | D76: =IF(ISBLANK(A76), D75, A76) -> Cabinets
B77: Magleby Construction, LLC | C77: (801) 785-9998 | D77: =IF(ISBLANK(A77), D76, A77) -> Cabinets
B78: Marwood Design | C78: (801) 414-9936 | D78: =IF(ISBLANK(A78), D77, A78) -> Cabinets
B79: Matt Caron Custom Cabinets, LLC | C79: (801) 404-3589 | D79: =IF(ISBLANK(A79), D78, A79) -> Cabinets
B80: Peterson Woodworks | C80: (801) 785-3990 | D80: =IF(ISBLANK(A80), D79, A80) -> Cabinets
B81: Precision Woodworking, Inc | C81: (801) 785-3527 | D81: =IF(ISBLANK(A81), D80, A81) -> Cabinets
B82: R & M Woods Inc | C82: (801) 226-2214 | D82: =IF(ISBLANK(A82), D81, A82) -> Cabinets
... B90: Xinja Built | C90: (385) 296-2186 | D90: =IF(ISBLANK(A90), D89, A90) -> Cabinets
A91: Cleaning Services | B91: Above and Beyond Cleaning | C91: (801) 400-1819 | D91: =IF(ISBLANK(A91), D90, A91) -> Cleaning Services
B92: Bee Neat Cleaning Co | C92: (801) 755-8240 | D92: =IF(ISBLANK(A92), D91, A92) -> Cleaning Services
B93: Clean and Tidy Utah | C93: (801) 310-5663 | D93: =IF(ISBLANK(A93), D92, A93) -> Cleaning Services
B94: JT SWPPP | C94: (435) 414-5212 | D94: =IF(ISBLANK(A94), D93, A94) -> Cleaning Services
B95: SmartClean Commercial Cleaning | C95: (801) 808-7294 | D95: =IF(ISBLANK(A95), D94, A95) -> Cleaning Services
B96: Window Genie of Provo | C96: (801) 623-6637 | D96: =IF(ISBLANK(A96), D95, A96) -> Cleaning Services
A97: Concrete Contractors | B97: DM Concrete Inc | C97: (801) 319-6457 | D97: =IF(ISBLANK(A97), D96, A97) -> Concrete Contractors
B98: Excel Concrete Incorporated | C98: (801) 420-1854 | D98: =IF(ISBLANK(A98), D97, A98) -> Concrete Contractors
B99: Fox Concrete | C99: (801) 717-7072 | D99: =IF(ISBLANK(A99), D98, A99) -> Concrete Contractors
B100: Great Western Inc | C100: (701) 609-6708 | D100: =IF(ISBLANK(A100), D99, A100) -> Concrete Contractors
B101: Harper Companies | C101: (801) 326-1016 | D101: =IF(ISBLANK(A101), D100, A101) -> Concrete Contractors
B102: Jeff Dumas Concrete Construction, LLC | C102: (801) 330-1873 | D102: =IF(ISBLANK(A102), D101, A102) -> Concrete Contractors
B103: Kenny Seng Construction | C103: (801) 226-4125 | D103: =IF(ISBLANK(A103), D102, A103) -> Concrete Contractors
B104: Nicoha | C104: (801) 338-3806 | D104: =IF(ISBLANK(A104), D103, A104) -> Concrete Contractors
B105: Premium Surface Solutions | C105: (801) 865-1934 | D105: =IF(ISBLANK(A105), D104, A105) -> Concrete Contractors
B106: Rocky Mountain Waterproofing | C106: (801) 282-2100 | D106: =IF(ISBLANK(A106), D105, A106) -> Concrete Contractors
B107: SMT Concrete | C107: (801) 837-9981 | D107: =IF(ISBLANK(A107), D106, A107) -> Concrete Contractors
B108: Viking Construction & Landscaping | C108: (801) 787-8893 | D108: =IF(ISBLANK(A108), D107, A108) -> Concrete Contractors
B109: Wrox, LLC | C109: (385) 412-9527 | D109: =IF(ISBLANK(A109), D108, A109) -> Concrete Contractors
A110: Countertops | B110: Acapulco Marble and Granite Inc | C110: (385) 216-8993 | D110: =IF(ISBLANK(A110), D109, A110) -> Countertops
B111: BC Countertops | C111: (801) 628-0604 | D111: =IF(ISBLANK(A111), D110, A111) -> Countertops
B112: Bedrock Quartz | C112: (801) 282-3322 | D112: =IF(ISBLANK(A112), D111, A112) -> Countertops
B113: Black Granite Installations LLC | C113: (801) 467-4439 | D113: =IF(ISBLANK(A113), D112, A113) -> Countertops
B114: Creative Granite & Designs | C114: (801) 886-0204 | D114: =IF(ISBLANK(A114), D113, A114) -> Countertops
B115: Graebridge Stone | C115: (801) 301-8981 | D115: =IF(ISBLANK(A115), D114, A115) -> Countertops
B116: MGS by Design | C116: (801) 722-0050 | D116: =IF(ISBLANK(A116), D115, A116) -> Countertops
B117: Petra Group | C117: (801) 486-1700 | D117: =IF(ISBLANK(A117), D116, A117) -> Countertops
B118: Rock Solid Granite | C118: (801) 225-0812 | D118: =IF(ISBLANK(A118), D117, A118) -> Countertops
...
